scr/yang_qiu_jun_we/__init__.py
scr/yang_qiu_jun_we/jun_wen.py
jun_wen-1.0.1.dist-info/LICENSE
jun_wen-1.0.1.dist-info/METADATA
jun_wen-1.0.1.dist-info/WHEEL
jun_wen-1.0.1.dist-info/top_level.txt
jun_wen-1.0.1.dist-info/RECORD
